birdnames/__init__.py
birdnames/converter.py
birdnames/data/available_taxonomies.csv
birdnames/data/processed/avilist_2025_taxonomy.csv
birdnames/data/processed/bbl_2025_taxonomy.csv
birdnames/data/processed/birdlife_2024_taxonomy.csv
birdnames/data/processed/ebird_2021_taxonomy.csv
birdnames/data/processed/ebird_2022_taxonomy.csv
birdnames/data/processed/ebird_2023_taxonomy.csv
birdnames/data/processed/ebird_2024_taxonomy.csv
birdnames/data/processed/ibp_2024_taxonomy.csv
birdnames/sources/__init__.py
birdnames/utils.py
birdnames-0.1.2.dist-info/LICENSE
birdnames-0.1.2.dist-info/METADATA
birdnames-0.1.2.dist-info/WHEEL
birdnames-0.1.2.dist-info/RECORD
