Metadata-Version: 2.3
Name: birdnames
Version: 0.1.2
Summary: A Python package for managing avian taxonomy and converting between different bird name formats across multiple taxonomic authorities
License: MIT
Keywords: ornithology,bird,taxonomy,names,species,conversion
Author: Sam Lapp
Author-email: sam.lapp@pitt.edu
Requires-Python: >=3.9,<4.0
Classifier: Development Status :: 4 - Beta
Classifier: Intended Audience :: Science/Research
Classifier: License :: OSI Approved :: MIT License
Classifier: Programming Language :: Python :: 3
Classifier: Programming Language :: Python :: 3.9
Classifier: Programming Language :: Python :: 3.10
Classifier: Programming Language :: Python :: 3.11
Classifier: Programming Language :: Python :: 3.12
Classifier: Programming Language :: Python :: 3.13
Classifier: Topic :: Scientific/Engineering :: Bio-Informatics
Classifier: Topic :: Software Development :: Libraries :: Python Modules
Requires-Dist: numpy (>=1.25.0)
Requires-Dist: openpyxl (>=3.1.0,<4.0.0)
Requires-Dist: pandas (>=2.0.0,<3.0.0)
Project-URL: Homepage, https://github.com/samlapp/birdnames
Project-URL: Repository, https://github.com/samlapp/birdnames
